airflow_providers_navitia-0.1.3.dist-info/licenses/LICENSE
navitia_provider/__init__.py
navitia_provider/hooks/__init__.py
navitia_provider/hooks/navitia.py
navitia_provider/operators/__init__.py
navitia_provider/operators/navitia.py
airflow_providers_navitia-0.1.3.dist-info/METADATA
airflow_providers_navitia-0.1.3.dist-info/WHEEL
airflow_providers_navitia-0.1.3.dist-info/entry_points.txt
airflow_providers_navitia-0.1.3.dist-info/top_level.txt
airflow_providers_navitia-0.1.3.dist-info/RECORD
