Metadata-Version: 2.4
Name: airflow-providers-navitia
Version: 0.1.3
Summary: Navitia hook and operator for Apache Airflow
Author-email: Jonathan Perron <jonathan@perron.bzh>
License-Expression: MIT
Project-URL: Source, https://github.com/jonperron/airflow-provider-navitia
Classifier: Framework :: Apache Airflow
Classifier: Framework :: Apache Airflow :: Provider
Requires-Python: >=3.10
License-File: LICENSE
Requires-Dist: apache-airflow>=2.10
Requires-Dist: apache-airflow-providers-postgres>=6.2.0
Requires-Dist: python-navitia-client>1.1.5
Dynamic: license-file
